LICENSE.txt
MANIFEST.in
README.rst
setup.py
tox.ini
docs/Makefile
docs/conf.py
docs/index.rst
docs/make.bat
planetmint_pymultihash.egg-info/PKG-INFO
planetmint_pymultihash.egg-info/SOURCES.txt
planetmint_pymultihash.egg-info/dependency_links.txt
planetmint_pymultihash.egg-info/requires.txt
planetmint_pymultihash.egg-info/top_level.txt
pymultihash/__init__.py
pymultihash/codecs.py
pymultihash/funcs.py
pymultihash/multihash.py
pymultihash/version.py
tests/__init__.py
tests/test_multihash.py