Metadata-Version: 2.1
Name: planetmint-pymultihash
Version: 0.9.2
Summary: Python implementation of the multihash specification
Home-page: https://github.com/planetmint/pymultihash
Author: Ivan Vilata-i-Balaguer
Author-email: ivan@selidor.net
License: MIT
Keywords: multihash hash digest format ASCII encoding
Classifier: Development Status :: 3 - Alpha
Classifier: Intended Audience :: Developers
Classifier: License :: OSI Approved :: MIT License
Classifier: Programming Language :: Python :: 3 :: Only
Classifier: Programming Language :: Python :: 3.4
Classifier: Programming Language :: Python :: 3.5
Classifier: Programming Language :: Python :: 3.6
Classifier: Programming Language :: Python :: 3.7
Classifier: Programming Language :: Python :: 3.8
Classifier: Programming Language :: Python :: 3.9
Classifier: Topic :: Security :: Cryptography
Provides-Extra: sha3
Provides-Extra: blake2
License-File: LICENSE.txt
